{
	"configurations" : 
	[
		{
			"directories" : 
			[
				{
					"build" : ".",
					"jsonFile" : "directory-.-Debug-f5ebdc15457944623624.json",
					"minimumCMakeVersion" : 
					{
						"string" : "3.16"
					},
					"projectIndex" : 0,
					"source" : ".",
					"targetIndexes" : 
					[
						0,
						1
					]
				}
			],
			"name" : "Debug",
			"projects" : 
			[
				{
					"directoryIndexes" : 
					[
						0
					],
					"name" : "Sort",
					"targetIndexes" : 
					[
						0,
						1
					]
				}
			],
			"targets" : 
			[
				{
					"directoryIndex" : 0,
					"id" : "Sort::@6890427a1f51a3e7e1df",
					"jsonFile" : "target-Sort-Debug-b6afbc6446abca25e046.json",
					"name" : "Sort",
					"projectIndex" : 0
				},
				{
					"directoryIndex" : 0,
					"id" : "Sort_autogen::@6890427a1f51a3e7e1df",
					"jsonFile" : "target-Sort_autogen-Debug-2584748da4ff7ca49e61.json",
					"name" : "Sort_autogen",
					"projectIndex" : 0
				}
			]
		}
	],
	"kind" : "codemodel",
	"paths" : 
	{
		"build" : "/home/andrey/labs/Lab4/Task1/build-Sort-Desktop-Debug",
		"source" : "/home/andrey/labs/Lab4/Task1/Sort"
	},
	"version" : 
	{
		"major" : 2,
		"minor" : 3
	}
}
